asposediagram/__init__.py
asposediagram/api.py
asposediagram/lib/DiagramJavaClassBridge.jar
asposediagram/lib/aspose-diagram-26.1.jar
aspose_diagram-26.1.0.dist-info/METADATA
aspose_diagram-26.1.0.dist-info/WHEEL
aspose_diagram-26.1.0.dist-info/top_level.txt
aspose_diagram-26.1.0.dist-info/RECORD
