Metadata-Version: 2.1
Name: aspose-diagram
Version: 26.1.0
Summary: A powerful library for working with Microsoft Visio files VDX, VSD,VSDX,VSSX,VSTX, VTX, XPS, HTML, SVG
Home-page: https://products.aspose.com/diagram/python-java
Author: Aspose
Author-email: diagram@aspose.com
Keywords: Visio,VSD,VDX,VSDX,VDW,to,PDF,JPG,PNG,HTML,SVG,XPS,VSTX,VSSX
Platform: Operating System :: MacOS :: MacOS X
Platform: Operating System :: Microsoft :: Windows :: Windows 7
Platform: Operating System :: Microsoft :: Windows :: Windows Vista
Platform: Operating System :: POSIX :: Linux
Classifier: Programming Language :: Python :: 3.5
Classifier: License :: Other/Proprietary License
Requires-Python: >=3.5
Requires-Dist: JPype1 >=1.2.1
